{
    "key": "group_59f01e5914f32",
    "title": "4.4.4. Listing Pagination",
    "fields": [
        {
            "key": "field_5800f7360c07a",
            "label": "",
            "name": "",
            "type": "message",
            "instructions": "",
            "required": 0,
            "conditional_logic": 0,
            "wrapper": {
                "width": "",
                "class": "acf-field--full-width",
                "id": ""
            },
            "message": "<img src=\"http:\/\/flothemes-dashboard-images.s3.amazonaws.com\/cube\/page-listing__pagination.jpg\" class=\"acf-img\"\/>",
            "esc_html": 0,
            "new_lines": "wpautop"
        },
        {
            "key": "field_5832cbb5c1818",
            "label": "A.1. Display Page Numbers",
            "name": "page-listing__page-numbers-enabled",
            "type": "true_false",
            "instructions": "",
            "required": 0,
            "conditional_logic": 0,
            "wrapper": {
                "width": "",
                "class": "",
                "id": ""
            },
            "default_value": 1,
            "message": "",
            "ui": 0,
            "ui_on_text": "",
            "ui_off_text": ""
        },
        {
            "key": "field_588b587c93cb5",
            "label": "A.2. Page Numbers Font",
            "name": "page-listing__page-numbers-font",
            "type": "font_style_select",
            "instructions": "",
            "required": 0,
            "conditional_logic": [
                [
                    {
                        "field": "field_5832cbb5c1818",
                        "operator": "==",
                        "value": "1"
                    }
                ]
            ],
            "wrapper": {
                "width": "",
                "class": "",
                "id": ""
            },
            "default_css_selectors": "",
            "active_css_selectors": "",
            "hover_css_selectors": "",
            "typography_option_name": "",
            "default_typography_style": "label_2"
        },
        {
            "key": "field_5832cbf4c1819",
            "label": "B. Display Navigation Buttons",
            "name": "page-listing__navigation-buttons-enabled",
            "type": "true_false",
            "instructions": "",
            "required": 0,
            "conditional_logic": 0,
            "wrapper": {
                "width": "",
                "class": "",
                "id": ""
            },
            "default_value": 1,
            "message": "",
            "ui": 0,
            "ui_on_text": "",
            "ui_off_text": ""
        }
    ],
    "location": [
        [
            {
                "param": "post_type",
                "operator": "==",
                "value": "post"
            }
        ]
    ],
    "menu_order": 0,
    "position": "normal",
    "style": "default",
    "label_placement": "top",
    "instruction_placement": "label",
    "hide_on_screen": "",
    "active": 0,
    "description": "",
    "modified": 1509356218
}