{
    "key": "group_5a1fec05bd336",
    "title": "Block. Video",
    "fields": [
        {
            "key": "field_5a1fec2f5b953",
            "label": "Overview",
            "name": "",
            "type": "message",
            "instructions": "",
            "required": 0,
            "conditional_logic": 0,
            "wrapper": {
                "width": "",
                "class": "acf-field--full-width",
                "id": ""
            },
            "message": "<img class=\"acf-img\" src=\"https:\/\/s3-us-west-2.amazonaws.com\/flothemes-dashboard-images\/cube\/flo-block-video.overview.jpg\" \/>",
            "new_lines": "wpautop",
            "esc_html": 0
        },
        {
            "key": "field_5a1fec9da880e",
            "label": "1. Merge with Header",
            "name": "flo-block__merge-with-header",
            "type": "true_false",
            "instructions": "",
            "required": 0,
            "conditional_logic": 0,
            "wrapper": {
                "width": "",
                "class": "",
                "id": ""
            },
            "message": "",
            "default_value": 1,
            "ui": 0,
            "ui_on_text": "",
            "ui_off_text": ""
        },
        {
            "key": "field_5a23a1be4d2c4",
            "label": "2. Elements Color",
            "name": "elements_color",
            "type": "color_picker",
            "instructions": "Default: #FFFFFF",
            "required": 0,
            "conditional_logic": 0,
            "wrapper": {
                "width": "",
                "class": "",
                "id": ""
            },
            "default_value": "#FFFFFF"
        },
        {
            "key": "field_5a1fecc4a880f",
            "label": "3. Video Embed Code",
            "name": "video_code",
            "type": "textarea",
            "instructions": "",
            "required": 1,
            "conditional_logic": 0,
            "wrapper": {
                "width": "",
                "class": "",
                "id": ""
            },
            "default_value": "",
            "placeholder": "",
            "maxlength": "",
            "rows": "",
            "new_lines": "wpautop"
        },
        {
            "key": "field_5a23a366ede3c",
            "label": "3.1. Video Cover Image",
            "name": "video_cover_image",
            "type": "image",
            "instructions": "",
            "required": 1,
            "conditional_logic": 0,
            "wrapper": {
                "width": "",
                "class": "",
                "id": ""
            },
            "return_format": "array",
            "preview_size": "thumbnail",
            "library": "all",
            "min_width": "",
            "min_height": "",
            "min_size": "",
            "max_width": "",
            "max_height": "",
            "max_size": "",
            "mime_types": ""
        },
        {
            "key": "field_5a23a303ede3a",
            "label": "3.2. Video Height",
            "name": "video_height",
            "type": "radio",
            "instructions": "",
            "required": 0,
            "conditional_logic": 0,
            "wrapper": {
                "width": "",
                "class": "",
                "id": ""
            },
            "choices": {
                "full": "Full Screen",
                "specific": "Specific"
            },
            "allow_null": 0,
            "other_choice": 0,
            "save_other_choice": 0,
            "default_value": "full",
            "layout": "vertical",
            "return_format": "value"
        },
        {
            "key": "field_5a23a338ede3b",
            "label": "3.2.1. Video Height in PX",
            "name": "video_height_in_px",
            "type": "number_slider",
            "instructions": "",
            "required": 0,
            "conditional_logic": [
                [
                    {
                        "field": "field_5a23a303ede3a",
                        "operator": "==",
                        "value": "specific"
                    }
                ]
            ],
            "wrapper": {
                "width": "",
                "class": "",
                "id": ""
            },
            "slider_units": "px",
            "default_value": 500,
            "slider_min_value": 300,
            "slider_max_value": 1000,
            "increment_value": 10
        },
        {
            "key": "field_5a23a204c7117",
            "label": "3.3. Play Button Icon Color",
            "name": "play_button_icon_color",
            "type": "color_picker",
            "instructions": "Default: #000000",
            "required": 0,
            "conditional_logic": 0,
            "wrapper": {
                "width": "",
                "class": "",
                "id": ""
            },
            "default_value": "#000000"
        },
        {
            "key": "field_5a1fed0da8810",
            "label": "4. Bottom Label",
            "name": "bottom_label",
            "type": "text",
            "instructions": "",
            "required": 0,
            "conditional_logic": 0,
            "wrapper": {
                "width": "",
                "class": "",
                "id": ""
            },
            "default_value": "SCROLL DOWN TO SEE MORE",
            "placeholder": "",
            "prepend": "",
            "append": "",
            "maxlength": ""
        },
        {
            "key": "field_5a1fed2fa8811",
            "label": "4.1. Bottom Label Font",
            "name": "bottom_label_font",
            "type": "font_style_select",
            "instructions": "Default: Label 2",
            "required": 0,
            "conditional_logic": 0,
            "wrapper": {
                "width": "",
                "class": "",
                "id": ""
            },
            "default_css_selectors": "",
            "active_css_selectors": "",
            "hover_css_selectors": "",
            "typography_option_name": "",
            "default_typography_style": "label_2"
        }
    ],
    "location": [
        [
            {
                "param": "post_type",
                "operator": "==",
                "value": "post"
            }
        ]
    ],
    "menu_order": 0,
    "position": "normal",
    "style": "default",
    "label_placement": "top",
    "instruction_placement": "label",
    "hide_on_screen": "",
    "active": 0,
    "description": "",
    "modified": 1512286238
}